LICENSE
MANIFEST.in
README.md
requirements.txt
setup.py
EmojiCaptcha/__init__.py
EmojiCaptcha/__main__.py
EmojiCaptcha/emojis_map.py
EmojiCaptcha.egg-info/PKG-INFO
EmojiCaptcha.egg-info/SOURCES.txt
EmojiCaptcha.egg-info/dependency_links.txt
EmojiCaptcha.egg-info/not-zip-safe
EmojiCaptcha.egg-info/requires.txt
EmojiCaptcha.egg-info/top_level.txt
EmojiCaptcha/emojis/1f0cf.png
EmojiCaptcha/emojis/1f300.png
EmojiCaptcha/emojis/1f302.png
EmojiCaptcha/emojis/1f311.png
EmojiCaptcha/emojis/1f315.png
EmojiCaptcha/emojis/1f321.png
EmojiCaptcha/emojis/1f324.png
EmojiCaptcha/emojis/1f325.png
EmojiCaptcha/emojis/1f326.png
EmojiCaptcha/emojis/1f327.png
EmojiCaptcha/emojis/1f328.png
EmojiCaptcha/emojis/1f329.png
EmojiCaptcha/emojis/1f32d.png
EmojiCaptcha/emojis/1f32e.png
EmojiCaptcha/emojis/1f32f.png
EmojiCaptcha/emojis/1f330.png
EmojiCaptcha/emojis/1f331.png
EmojiCaptcha/emojis/1f332.png
EmojiCaptcha/emojis/1f333.png
EmojiCaptcha/emojis/1f334.png
EmojiCaptcha/emojis/1f335.png
EmojiCaptcha/emojis/1f336.png
EmojiCaptcha/emojis/1f337.png
EmojiCaptcha/emojis/1f338.png
EmojiCaptcha/emojis/1f339.png
EmojiCaptcha/emojis/1f33a.png
EmojiCaptcha/emojis/1f33b.png
EmojiCaptcha/emojis/1f33c.png
EmojiCaptcha/emojis/1f33d.png
EmojiCaptcha/emojis/1f33e.png
EmojiCaptcha/emojis/1f33f.png
EmojiCaptcha/emojis/1f340.png
EmojiCaptcha/emojis/1f341.png
EmojiCaptcha/emojis/1f342.png
EmojiCaptcha/emojis/1f343.png
EmojiCaptcha/emojis/1f344.png
EmojiCaptcha/emojis/1f345.png
EmojiCaptcha/emojis/1f346.png
EmojiCaptcha/emojis/1f347.png
EmojiCaptcha/emojis/1f348.png
EmojiCaptcha/emojis/1f349.png
EmojiCaptcha/emojis/1f34a.png
EmojiCaptcha/emojis/1f34b.png
EmojiCaptcha/emojis/1f34c.png
EmojiCaptcha/emojis/1f34d.png
EmojiCaptcha/emojis/1f34e.png
EmojiCaptcha/emojis/1f34f.png
EmojiCaptcha/emojis/1f350.png
EmojiCaptcha/emojis/1f351.png
EmojiCaptcha/emojis/1f352.png
EmojiCaptcha/emojis/1f353.png
EmojiCaptcha/emojis/1f354.png
EmojiCaptcha/emojis/1f355.png
EmojiCaptcha/emojis/1f356.png
EmojiCaptcha/emojis/1f357.png
EmojiCaptcha/emojis/1f358.png
EmojiCaptcha/emojis/1f359.png
EmojiCaptcha/emojis/1f35a.png
EmojiCaptcha/emojis/1f35b.png
EmojiCaptcha/emojis/1f35c.png
EmojiCaptcha/emojis/1f35d.png
EmojiCaptcha/emojis/1f35e.png
